patch_file_mcp/__init__.py
patch_file_mcp/server.py
patch_file_mcp-0.1.0.dist-info/licenses/LICENSE
patch_file_mcp-0.1.0.dist-info/METADATA
patch_file_mcp-0.1.0.dist-info/WHEEL
patch_file_mcp-0.1.0.dist-info/entry_points.txt
patch_file_mcp-0.1.0.dist-info/top_level.txt
patch_file_mcp-0.1.0.dist-info/RECORD
