Metadata-Version: 2.4
Name: patch-file-mcp
Version: 0.1.0
Summary: An MCP Server to patch existing files
Author: PYNESYS LLC
License: MIT
Requires-Python: >=3.11
License-File: LICENSE
Requires-Dist: fastmcp<3.0.0,>=2.2.0
Dynamic: license-file
